{
  "type": "minecraft:block",
  "pools": [
    {
      "bonus_rolls": 0.0,
      "conditions": [
        {
          "condition": "minecraft:survives_explosion"
        }
      ],
      "entries": [
        {
          "type": "minecraft:item",
          "name": "mirage2004:prefab_window_balcony_black_blue_balcony_left",
          "conditions": [
            {
              "condition": "minecraft:block_state_property",
              "block": "mirage2004:prefab_window_balcony_black_blue_balcony_left",
              "properties": {
                "half": "lower"
              }
            }
          ]
        }
      ],
      "rolls": 1.0
    }
  ],
  "random_sequence": "mirage2004:blocks/prefab_window_balcony_black_blue_balcony_left"
}
